lyk_reservation/__init__.py
lyk_reservation/reservation.py
lyk_reservation_nowon-0.0.8.dist-info/METADATA
lyk_reservation_nowon-0.0.8.dist-info/WHEEL
lyk_reservation_nowon-0.0.8.dist-info/top_level.txt
lyk_reservation_nowon-0.0.8.dist-info/RECORD
