Metadata-Version: 2.1
Name: lyk-reservation-nowon
Version: 0.0.8
Summary: lyk-reservation-nowon
Author: officeyongki
Author-email: officeyongki@gmail.com
Keywords: reservation,lyk,pypi
Classifier: Programming Language :: Python :: 3.6
Classifier: Programming Language :: Python :: 3.7
Classifier: Programming Language :: Python :: 3.8
Classifier: Programming Language :: Python :: 3.9
Classifier: Programming Language :: Python :: 3.10
Classifier: Programming Language :: Python :: 3.11
Requires-Python: >=3.10
Requires-Dist: pyperclip
Requires-Dist: selenium
Requires-Dist: webdriver-manager
